phable/__init__.py
phable/grid_builder.py
phable/haxall_client.py
phable/haystack_client.py
phable/http.py
phable/kinds.py
phable/logger.py
phable/py.typed
phable/xeto_cli.py
phable/auth/__init__.py
phable/auth/scram.py
phable/io/__init__.py
phable/io/json_decoder.py
phable/io/json_encoder.py
phable/io/ph_decoder.py
phable/io/ph_encoder.py
phable/io/ph_io_factory.py
phable/io/ph_tokenizer.py
phable/io/zinc_decoder.py
phable/io/zinc_encoder.py
phable-0.1.25.dist-info/METADATA
phable-0.1.25.dist-info/WHEEL
phable-0.1.25.dist-info/licenses/LICENSE
phable-0.1.25.dist-info/RECORD
