Metadata-Version: 2.4
Name: phable
Version: 0.1.25
Author-email: Rick Jennings <rjennings055@gmail.com>
License-Expression: MIT
License-File: LICENSE
Requires-Python: <4,>=3.11
Provides-Extra: pandas
Requires-Dist: pandas<3,>=2.2.3; extra == 'pandas'
Provides-Extra: polars
Requires-Dist: polars<2,>=1.9.0; extra == 'polars'
Provides-Extra: pyarrow
Requires-Dist: pyarrow<18,>=17.0.0; extra == 'pyarrow'
